{"copyright": "NHL and the NHL Shield are registered trademarks of the National Hockey League. NHL and NHL team marks are the property of the NHL and its teams. \u00a9 NHL 2019. All Rights Reserved.", "roster": [{"person": {"id": 8447091, "fullName": "Martin Gelinas", "link": "/api/v1/people/8447091"}, "jerseyNumber": "23", "position": {"code": "L", "name": "Left Wing", "type": "Forward", "abbreviation": "LW"}}, {"person": {"id": 8459429, "fullName": "Jason Arnott", "link": "/api/v1/people/8459429"}, "jerseyNumber": "44", "position": {"code": "C", "name": "Center", "type": "Forward", "abbreviation": "C"}}, {"person": {"id": 8459687, "fullName": "Scott Nichol", "link": "/api/v1/people/8459687"}, "jerseyNumber": "12", "position": {"code": "C", "name": "Center", "type": "Forward", "abbreviation": "C"}}, {"person": {"id": 8460105, "fullName": "Radek Bonk", "link": "/api/v1/people/8460105"}, "jerseyNumber": "14", "position": {"code": "C", "name": "Center", "type": "Forward", "abbreviation": "C"}}, {"person": {"id": 8460254, "fullName": "Greg De Vries", "link": "/api/v1/people/8460254"}, "jerseyNumber": "7", "position": {"code": "D", "name": "Defenseman", "type": "Defenseman", "abbreviation": "D"}}, {"person": {"id": 8462081, "fullName": "Jan Hlavac", "link": "/api/v1/people/8462081"}, "jerseyNumber": "17", "position": {"code": "L", "name": "Left Wing", "type": "Forward", "abbreviation": "LW"}}, {"person": {"id": 8464957, "fullName": "J-P Dumont", "link": "/api/v1/people/8464957"}, "jerseyNumber": "71", "position": {"code": "R", "name": "Right Wing", "type": "Forward", "abbreviation": "RW"}}, {"person": {"id": 8466200, "fullName": "Josh Langfeld", "link": "/api/v1/people/8466200"}, "jerseyNumber": "15", "position": {"code": "R", "name": "Right Wing", "type": "Forward", "abbreviation": "RW"}}, {"person": {"id": 8467330, "fullName": "David Legwand", "link": "/api/v1/people/8467330"}, "jerseyNumber": "17", "position": {"code": "C", "name": "Center", "type": "Forward", "abbreviation": "C"}}, {"person": {"id": 8468064, "fullName": "Martin Erat", "link": "/api/v1/people/8468064"}, "jerseyNumber": "10", "position": {"code": "R", "name": "Right Wing", "type": "Forward", "abbreviation": "RW"}}, {"person": {"id": 8468162, "fullName": "Jerred Smithson", "link": "/api/v1/people/8468162"}, "jerseyNumber": "22", "position": {"code": "C", "name": "Center", "type": "Forward", "abbreviation": "C"}}, {"person": {"id": 8468636, "fullName": "Greg Zanon", "link": "/api/v1/people/8468636"}, "jerseyNumber": "4", "position": {"code": "D", "name": "Defenseman", "type": "Defenseman", "abbreviation": "D"}}, {"person": {"id": 8468660, "fullName": "Darcy Hordichuk", "link": "/api/v1/people/8468660"}, "jerseyNumber": "16", "position": {"code": "L", "name": "Left Wing", "type": "Forward", "abbreviation": "LW"}}, {"person": {"id": 8469465, "fullName": "Dan Hamhuis", "link": "/api/v1/people/8469465"}, "jerseyNumber": "5", "position": {"code": "D", "name": "Defenseman", "type": "Defenseman", "abbreviation": "D"}}, {"person": {"id": 8469547, "fullName": "Jordin Tootoo", "link": "/api/v1/people/8469547"}, "jerseyNumber": "22", "position": {"code": "R", "name": "Right Wing", "type": "Forward", "abbreviation": "RW"}}, {"person": {"id": 8469623, "fullName": "Marek Zidlicky", "link": "/api/v1/people/8469623"}, "jerseyNumber": "28", "position": {"code": "D", "name": "Defenseman", "type": "Defenseman", "abbreviation": "D"}}, {"person": {"id": 8469666, "fullName": "Brandon Bochenski", "link": "/api/v1/people/8469666"}, "jerseyNumber": "27", "position": {"code": "R", "name": "Right Wing", "type": "Forward", "abbreviation": "RW"}}, {"person": {"id": 8469759, "fullName": "Vernon Fiddler", "link": "/api/v1/people/8469759"}, "jerseyNumber": "83", "position": {"code": "C", "name": "Center", "type": "Forward", "abbreviation": "C"}}, {"person": {"id": 8470580, "fullName": "Jed Ortmeyer", "link": "/api/v1/people/8470580"}, "jerseyNumber": "41", "position": {"code": "R", "name": "Right Wing", "type": "Forward", "abbreviation": "RW"}}, {"person": {"id": 8470600, "fullName": "Ryan Suter", "link": "/api/v1/people/8470600"}, "jerseyNumber": "20", "position": {"code": "D", "name": "Defenseman", "type": "Defenseman", "abbreviation": "D"}}, {"person": {"id": 8470630, "fullName": "Kevin Klein", "link": "/api/v1/people/8470630"}, "jerseyNumber": "8", "position": {"code": "D", "name": "Defenseman", "type": "Defenseman", "abbreviation": "D"}}, {"person": {"id": 8470642, "fullName": "Shea Weber", "link": "/api/v1/people/8470642"}, "jerseyNumber": "6", "position": {"code": "D", "name": "Defenseman", "type": "Defenseman", "abbreviation": "D"}}, {"person": {"id": 8471228, "fullName": "Alexander Radulov", "link": "/api/v1/people/8471228"}, "jerseyNumber": "47", "position": {"code": "R", "name": "Right Wing", "type": "Forward", "abbreviation": "RW"}}, {"person": {"id": 8471514, "fullName": "Rich Peverley", "link": "/api/v1/people/8471514"}, "jerseyNumber": "17", "position": {"code": "C", "name": "Center", "type": "Forward", "abbreviation": "C"}}, {"person": {"id": 8473385, "fullName": "Ville Koistinen", "link": "/api/v1/people/8473385"}, "jerseyNumber": "6", "position": {"code": "D", "name": "Defenseman", "type": "Defenseman", "abbreviation": "D"}}, {"person": {"id": 8473973, "fullName": "Antti Pihlstrom", "link": "/api/v1/people/8473973"}, "jerseyNumber": "42", "position": {"code": "L", "name": "Left Wing", "type": "Forward", "abbreviation": "LW"}}, {"person": {"id": 8462152, "fullName": "Chris Mason", "link": "/api/v1/people/8462152"}, "jerseyNumber": "30", "position": {"code": "G", "name": "Goalie", "type": "Goalie", "abbreviation": "G"}}, {"person": {"id": 8468540, "fullName": "Dan Ellis", "link": "/api/v1/people/8468540"}, "jerseyNumber": "39", "position": {"code": "G", "name": "Goalie", "type": "Goalie", "abbreviation": "G"}}, {"person": {"id": 8471469, "fullName": "Pekka Rinne", "link": "/api/v1/people/8471469"}, "jerseyNumber": "35", "position": {"code": "G", "name": "Goalie", "type": "Goalie", "abbreviation": "G"}}], "link": "/api/v1/teams/18/roster"}