{"copyright": "NHL and the NHL Shield are registered trademarks of the National Hockey League. NHL and NHL team marks are the property of the NHL and its teams. \u00a9 NHL 2019. All Rights Reserved.", "roster": [{"person": {"id": 8445550, "fullName": "Rob Blake", "link": "/api/v1/people/8445550"}, "jerseyNumber": "4", "position": {"code": "D", "name": "Defenseman", "type": "Defenseman", "abbreviation": "D"}}, {"person": {"id": 8451972, "fullName": "Scott Thornton", "link": "/api/v1/people/8451972"}, "jerseyNumber": "27", "position": {"code": "L", "name": "Left Wing", "type": "Forward", "abbreviation": "LW"}}, {"person": {"id": 8456852, "fullName": "Jon Klemm", "link": "/api/v1/people/8456852"}, "jerseyNumber": "25", "position": {"code": "D", "name": "Defenseman", "type": "Defenseman", "abbreviation": "D"}}, {"person": {"id": 8457403, "fullName": "Jaroslav Modry", "link": "/api/v1/people/8457403"}, "jerseyNumber": "26", "position": {"code": "D", "name": "Defenseman", "type": "Defenseman", "abbreviation": "D"}}, {"person": {"id": 8459064, "fullName": "Derek Armstrong", "link": "/api/v1/people/8459064"}, "jerseyNumber": "17", "position": {"code": "C", "name": "Center", "type": "Forward", "abbreviation": "C"}}, {"person": {"id": 8462129, "fullName": "Michal Handzus", "link": "/api/v1/people/8462129"}, "jerseyNumber": "26", "position": {"code": "C", "name": "Center", "type": "Forward", "abbreviation": "C"}}, {"person": {"id": 8465113, "fullName": "Brian Willsie", "link": "/api/v1/people/8465113"}, "jerseyNumber": "21", "position": {"code": "R", "name": "Right Wing", "type": "Forward", "abbreviation": "RW"}}, {"person": {"id": 8466260, "fullName": "Kyle Calder", "link": "/api/v1/people/8466260"}, "jerseyNumber": "32", "position": {"code": "L", "name": "Left Wing", "type": "Forward", "abbreviation": "LW"}}, {"person": {"id": 8466304, "fullName": "Ladislav Nagy", "link": "/api/v1/people/8466304"}, "jerseyNumber": "47", "position": {"code": "L", "name": "Left Wing", "type": "Forward", "abbreviation": "LW"}}, {"person": {"id": 8467331, "fullName": "Brad Stuart", "link": "/api/v1/people/8467331"}, "jerseyNumber": "17", "position": {"code": "D", "name": "Defenseman", "type": "Defenseman", "abbreviation": "D"}}, {"person": {"id": 8468500, "fullName": "Alex Frolov", "link": "/api/v1/people/8468500"}, "jerseyNumber": "31", "position": {"code": "L", "name": "Left Wing", "type": "Forward", "abbreviation": "LW"}}, {"person": {"id": 8468598, "fullName": "Lubomir Visnovsky", "link": "/api/v1/people/8468598"}, "jerseyNumber": "11", "position": {"code": "D", "name": "Defenseman", "type": "Defenseman", "abbreviation": "D"}}, {"person": {"id": 8469120, "fullName": "Raitis Ivanans", "link": "/api/v1/people/8469120"}, "jerseyNumber": "41", "position": {"code": "L", "name": "Left Wing", "type": "Forward", "abbreviation": "LW"}}, {"person": {"id": 8469500, "fullName": "Michael Cammalleri", "link": "/api/v1/people/8469500"}, "jerseyNumber": "13", "position": {"code": "L", "name": "Left Wing", "type": "Forward", "abbreviation": "LW"}}, {"person": {"id": 8469795, "fullName": "Kevin Dallman", "link": "/api/v1/people/8469795"}, "jerseyNumber": "38", "position": {"code": "D", "name": "Defenseman", "type": "Defenseman", "abbreviation": "D"}}, {"person": {"id": 8470001, "fullName": "Jeff Giuliano", "link": "/api/v1/people/8470001"}, "jerseyNumber": "29", "position": {"code": "L", "name": "Left Wing", "type": "Forward", "abbreviation": "LW"}}, {"person": {"id": 8470018, "fullName": "Matt Ellis", "link": "/api/v1/people/8470018"}, "jerseyNumber": "37", "position": {"code": "L", "name": "Left Wing", "type": "Forward", "abbreviation": "LW"}}, {"person": {"id": 8470113, "fullName": "John Zeiler", "link": "/api/v1/people/8470113"}, "jerseyNumber": "29", "position": {"code": "R", "name": "Right Wing", "type": "Forward", "abbreviation": "RW"}}, {"person": {"id": 8470575, "fullName": "Tom Preissing", "link": "/api/v1/people/8470575"}, "jerseyNumber": "20", "position": {"code": "D", "name": "Defenseman", "type": "Defenseman", "abbreviation": "D"}}, {"person": {"id": 8470606, "fullName": "Dustin Brown", "link": "/api/v1/people/8470606"}, "jerseyNumber": "23", "position": {"code": "R", "name": "Right Wing", "type": "Forward", "abbreviation": "RW"}}, {"person": {"id": 8470619, "fullName": "Brian Boyle", "link": "/api/v1/people/8470619"}, "jerseyNumber": "9", "position": {"code": "C", "name": "Center", "type": "Forward", "abbreviation": "C"}}, {"person": {"id": 8470649, "fullName": "Patrick O'Sullivan", "link": "/api/v1/people/8470649"}, "jerseyNumber": "18", "position": {"code": "C", "name": "Center", "type": "Forward", "abbreviation": "C"}}, {"person": {"id": 8470744, "fullName": "Brady Murray", "link": "/api/v1/people/8470744"}, "jerseyNumber": "15", "position": {"code": "L", "name": "Left Wing", "type": "Forward", "abbreviation": "LW"}}, {"person": {"id": 8470852, "fullName": "Matt Moulson", "link": "/api/v1/people/8470852"}, "position": {"code": "L", "name": "Left Wing", "type": "Forward", "abbreviation": "LW"}}, {"person": {"id": 8471224, "fullName": "Lauri Tukonen", "link": "/api/v1/people/8471224"}, "jerseyNumber": "34", "position": {"code": "R", "name": "Right Wing", "type": "Forward", "abbreviation": "RW"}}, {"person": {"id": 8471677, "fullName": "Jack Johnson", "link": "/api/v1/people/8471677"}, "jerseyNumber": "3", "position": {"code": "D", "name": "Defenseman", "type": "Defenseman", "abbreviation": "D"}}, {"person": {"id": 8471685, "fullName": "Anze Kopitar", "link": "/api/v1/people/8471685"}, "jerseyNumber": "11", "position": {"code": "C", "name": "Center", "type": "Forward", "abbreviation": "C"}}, {"person": {"id": 8472394, "fullName": "Peter Harrold", "link": "/api/v1/people/8472394"}, "jerseyNumber": "37", "position": {"code": "D", "name": "Defenseman", "type": "Defenseman", "abbreviation": "D"}}, {"person": {"id": 8473644, "fullName": "Gabe Gauthier", "link": "/api/v1/people/8473644"}, "jerseyNumber": "52", "position": {"code": "L", "name": "Left Wing", "type": "Forward", "abbreviation": "LW"}}, {"person": {"id": 8473962, "fullName": "Teddy Purcell", "link": "/api/v1/people/8473962"}, "jerseyNumber": "9", "position": {"code": "L", "name": "Left Wing", "type": "Forward", "abbreviation": "LW"}}, {"person": {"id": 8460516, "fullName": "Dan Cloutier", "link": "/api/v1/people/8460516"}, "jerseyNumber": "39", "position": {"code": "G", "name": "Goalie", "type": "Goalie", "abbreviation": "G"}}, {"person": {"id": 8462102, "fullName": "Jean-Sebastien Aubin", "link": "/api/v1/people/8462102"}, "jerseyNumber": "30", "position": {"code": "G", "name": "Goalie", "type": "Goalie", "abbreviation": "G"}}, {"person": {"id": 8467391, "fullName": "Jason LaBarbera", "link": "/api/v1/people/8467391"}, "jerseyNumber": "45", "position": {"code": "G", "name": "Goalie", "type": "Goalie", "abbreviation": "G"}}, {"person": {"id": 8471433, "fullName": "Daniel Taylor", "link": "/api/v1/people/8471433"}, "jerseyNumber": "70", "position": {"code": "G", "name": "Goalie", "type": "Goalie", "abbreviation": "G"}}, {"person": {"id": 8471734, "fullName": "Jonathan Quick", "link": "/api/v1/people/8471734"}, "jerseyNumber": "32", "position": {"code": "G", "name": "Goalie", "type": "Goalie", "abbreviation": "G"}}, {"person": {"id": 8473541, "fullName": "Jonathan Bernier", "link": "/api/v1/people/8473541"}, "jerseyNumber": "45", "position": {"code": "G", "name": "Goalie", "type": "Goalie", "abbreviation": "G"}}, {"person": {"id": 8473975, "fullName": "Erik Ersberg", "link": "/api/v1/people/8473975"}, "jerseyNumber": "31", "position": {"code": "G", "name": "Goalie", "type": "Goalie", "abbreviation": "G"}}], "link": "/api/v1/teams/26/roster"}