{"copyright": "NHL and the NHL Shield are registered trademarks of the National Hockey League. NHL and NHL team marks are the property of the NHL and its teams. \u00a9 NHL 2019. All Rights Reserved.", "roster": [{"person": {"id": 8460556, "fullName": "Freddy Modin", "link": "/api/v1/people/8460556"}, "jerseyNumber": "19", "position": {"code": "L", "name": "Left Wing", "type": "Forward", "abbreviation": "LW"}}, {"person": {"id": 8460567, "fullName": "Chris Clark", "link": "/api/v1/people/8460567"}, "jerseyNumber": "71", "position": {"code": "R", "name": "Right Wing", "type": "Forward", "abbreviation": "RW"}}, {"person": {"id": 8465192, "fullName": "Samuel Pahlsson", "link": "/api/v1/people/8465192"}, "jerseyNumber": "26", "position": {"code": "C", "name": "Center", "type": "Forward", "abbreviation": "C"}}, {"person": {"id": 8466181, "fullName": "Kristian Huselius", "link": "/api/v1/people/8466181"}, "jerseyNumber": "20", "position": {"code": "L", "name": "Left Wing", "type": "Forward", "abbreviation": "LW"}}, {"person": {"id": 8466251, "fullName": "Jason Chimera", "link": "/api/v1/people/8466251"}, "jerseyNumber": "20", "position": {"code": "L", "name": "Left Wing", "type": "Forward", "abbreviation": "LW"}}, {"person": {"id": 8467915, "fullName": "Mike Commodore", "link": "/api/v1/people/8467915"}, "jerseyNumber": "23", "position": {"code": "D", "name": "Defenseman", "type": "Defenseman", "abbreviation": "D"}}, {"person": {"id": 8468001, "fullName": "Derek MacKenzie", "link": "/api/v1/people/8468001"}, "jerseyNumber": "17", "position": {"code": "C", "name": "Center", "type": "Forward", "abbreviation": "C"}}, {"person": {"id": 8468484, "fullName": "Rostislav Klesla", "link": "/api/v1/people/8468484"}, "jerseyNumber": "97", "position": {"code": "D", "name": "Defenseman", "type": "Defenseman", "abbreviation": "D"}}, {"person": {"id": 8468485, "fullName": "Raffi Torres", "link": "/api/v1/people/8468485"}, "jerseyNumber": "13", "position": {"code": "L", "name": "Left Wing", "type": "Forward", "abbreviation": "LW"}}, {"person": {"id": 8468535, "fullName": "Antoine Vermette", "link": "/api/v1/people/8468535"}, "jerseyNumber": "50", "position": {"code": "C", "name": "Center", "type": "Forward", "abbreviation": "C"}}, {"person": {"id": 8469469, "fullName": "R.J. Umberger", "link": "/api/v1/people/8469469"}, "jerseyNumber": "20", "position": {"code": "C", "name": "Center", "type": "Forward", "abbreviation": "C"}}, {"person": {"id": 8469492, "fullName": "Fedor Tyutin", "link": "/api/v1/people/8469492"}, "jerseyNumber": "51", "position": {"code": "D", "name": "Defenseman", "type": "Defenseman", "abbreviation": "D"}}, {"person": {"id": 8469509, "fullName": "Nathan Paetsch", "link": "/api/v1/people/8469509"}, "jerseyNumber": "17", "position": {"code": "D", "name": "Defenseman", "type": "Defenseman", "abbreviation": "D"}}, {"person": {"id": 8469684, "fullName": "Milan Jurcina", "link": "/api/v1/people/8469684"}, "jerseyNumber": "27", "position": {"code": "D", "name": "Defenseman", "type": "Defenseman", "abbreviation": "D"}}, {"person": {"id": 8469685, "fullName": "Andrew Murray", "link": "/api/v1/people/8469685"}, "jerseyNumber": "23", "position": {"code": "C", "name": "Center", "type": "Forward", "abbreviation": "C"}}, {"person": {"id": 8470041, "fullName": "Rick Nash", "link": "/api/v1/people/8470041"}, "jerseyNumber": "61", "position": {"code": "L", "name": "Left Wing", "type": "Forward", "abbreviation": "LW"}}, {"person": {"id": 8470699, "fullName": "Jan Hejda", "link": "/api/v1/people/8470699"}, "jerseyNumber": "8", "position": {"code": "D", "name": "Defenseman", "type": "Defenseman", "abbreviation": "D"}}, {"person": {"id": 8470735, "fullName": "Greg Moore", "link": "/api/v1/people/8470735"}, "jerseyNumber": "49", "position": {"code": "R", "name": "Right Wing", "type": "Forward", "abbreviation": "RW"}}, {"person": {"id": 8470760, "fullName": "Marc Methot", "link": "/api/v1/people/8470760"}, "jerseyNumber": "33", "position": {"code": "D", "name": "Defenseman", "type": "Defenseman", "abbreviation": "D"}}, {"person": {"id": 8470804, "fullName": "Mathieu Roy", "link": "/api/v1/people/8470804"}, "jerseyNumber": "7", "position": {"code": "D", "name": "Defenseman", "type": "Defenseman", "abbreviation": "D"}}, {"person": {"id": 8471221, "fullName": "Alexandre Picard", "link": "/api/v1/people/8471221"}, "jerseyNumber": "19", "position": {"code": "L", "name": "Left Wing", "type": "Forward", "abbreviation": "LW"}}, {"person": {"id": 8471411, "fullName": "Chad Kolarik", "link": "/api/v1/people/8471411"}, "jerseyNumber": "25", "position": {"code": "C", "name": "Center", "type": "Forward", "abbreviation": "C"}}, {"person": {"id": 8471482, "fullName": "Grant Clitsome", "link": "/api/v1/people/8471482"}, "jerseyNumber": "24", "position": {"code": "D", "name": "Defenseman", "type": "Defenseman", "abbreviation": "D"}}, {"person": {"id": 8471663, "fullName": "Mike Blunden", "link": "/api/v1/people/8471663"}, "jerseyNumber": "20", "position": {"code": "R", "name": "Right Wing", "type": "Forward", "abbreviation": "RW"}}, {"person": {"id": 8471729, "fullName": "Kris Russell", "link": "/api/v1/people/8471729"}, "jerseyNumber": "4", "position": {"code": "D", "name": "Defenseman", "type": "Defenseman", "abbreviation": "D"}}, {"person": {"id": 8471766, "fullName": "Jared Boll", "link": "/api/v1/people/8471766"}, "jerseyNumber": "40", "position": {"code": "R", "name": "Right Wing", "type": "Forward", "abbreviation": "RW"}}, {"person": {"id": 8471873, "fullName": "Anton Stralman", "link": "/api/v1/people/8471873"}, "jerseyNumber": "6", "position": {"code": "D", "name": "Defenseman", "type": "Defenseman", "abbreviation": "D"}}, {"person": {"id": 8473432, "fullName": "Derek Dorsett", "link": "/api/v1/people/8473432"}, "position": {"code": "R", "name": "Right Wing", "type": "Forward", "abbreviation": "RW"}}, {"person": {"id": 8473491, "fullName": "Tomas Kana", "link": "/api/v1/people/8473491"}, "jerseyNumber": "46", "position": {"code": "C", "name": "Center", "type": "Forward", "abbreviation": "C"}}, {"person": {"id": 8473542, "fullName": "Tom Sestito", "link": "/api/v1/people/8473542"}, "jerseyNumber": "25", "position": {"code": "L", "name": "Left Wing", "type": "Forward", "abbreviation": "LW"}}, {"person": {"id": 8473544, "fullName": "Derick Brassard", "link": "/api/v1/people/8473544"}, "jerseyNumber": "10", "position": {"code": "C", "name": "Center", "type": "Forward", "abbreviation": "C"}}, {"person": {"id": 8473687, "fullName": "Trevor Frischmon", "link": "/api/v1/people/8473687"}, "jerseyNumber": "28", "position": {"code": "C", "name": "Center", "type": "Forward", "abbreviation": "C"}}, {"person": {"id": 8474161, "fullName": "Jakub Voracek", "link": "/api/v1/people/8474161"}, "jerseyNumber": "93", "position": {"code": "R", "name": "Right Wing", "type": "Forward", "abbreviation": "RW"}}, {"person": {"id": 8474195, "fullName": "Maksim Mayorov", "link": "/api/v1/people/8474195"}, "jerseyNumber": "8", "position": {"code": "L", "name": "Left Wing", "type": "Forward", "abbreviation": "LW"}}, {"person": {"id": 8474566, "fullName": "Nikita Filatov", "link": "/api/v1/people/8474566"}, "jerseyNumber": "21", "position": {"code": "L", "name": "Left Wing", "type": "Forward", "abbreviation": "LW"}}, {"person": {"id": 8464999, "fullName": "Mathieu Garon", "link": "/api/v1/people/8464999"}, "jerseyNumber": "32", "position": {"code": "G", "name": "Goalie", "type": "Goalie", "abbreviation": "G"}}, {"person": {"id": 8473461, "fullName": "Steve Mason", "link": "/api/v1/people/8473461"}, "position": {"code": "G", "name": "Goalie", "type": "Goalie", "abbreviation": "G"}}], "link": "/api/v1/teams/29/roster"}