[{"id": 8468011, "fullName": "Ryan Miller", "link": "/api/v1/people/8468011", "firstName": "Ryan", "lastName": "Miller", "primaryNumber": "30", "birthDate": "1980-07-17", "currentAge": 39, "birthCity": "East Lansing", "birthStateProvince": "MI", "birthCountry": "USA", "nationality": "USA", "height": "6' 2\"", "weight": 170, "active": true, "alternateCaptain": false, "captain": false, "rookie": false, "shootsCatches": "L", "rosterStatus": "Y", "currentTeam": {"id": 24, "name": "Anaheim Ducks", "link": "/api/v1/teams/24"}, "primaryPosition": {"code": "G", "name": "Goalie", "type": "Goalie", "abbreviation": "G"}}]