[{"id": 8469608, "fullName": "Mike Smith", "link": "/api/v1/people/8469608", "firstName": "Mike", "lastName": "Smith", "primaryNumber": "41", "birthDate": "1982-03-22", "currentAge": 37, "birthCity": "Kingston", "birthStateProvince": "ON", "birthCountry": "CAN", "nationality": "CAN", "height": "6' 5\"", "weight": 220, "active": true, "alternateCaptain": false, "captain": false, "rookie": false, "shootsCatches": "L", "rosterStatus": "Y", "currentTeam": {"id": 22, "name": "Edmonton Oilers", "link": "/api/v1/teams/22"}, "primaryPosition": {"code": "G", "name": "Goalie", "type": "Goalie", "abbreviation": "G"}}]