[{"id": 8471691, "fullName": "Martin Hanzal", "link": "/api/v1/people/8471691", "firstName": "Martin", "lastName": "Hanzal", "primaryNumber": "40", "birthDate": "1987-02-20", "currentAge": 32, "birthCity": "Pisek", "birthCountry": "CZE", "nationality": "CZE", "height": "6' 6\"", "weight": 230, "active": true, "alternateCaptain": false, "captain": false, "rookie": false, "shootsCatches": "L", "rosterStatus": "I", "currentTeam": {"id": 25, "name": "Dallas Stars", "link": "/api/v1/teams/25"}, "primaryPosition": {"code": "C", "name": "Center", "type": "Forward", "abbreviation": "C"}}]