[{"id": 8471227, "fullName": "Devan Dubnyk", "link": "/api/v1/people/8471227", "firstName": "Devan", "lastName": "Dubnyk", "primaryNumber": "40", "birthDate": "1986-05-04", "currentAge": 33, "birthCity": "Regina", "birthStateProvince": "SK", "birthCountry": "CAN", "nationality": "CAN", "height": "6' 6\"", "weight": 224, "active": true, "alternateCaptain": false, "captain": false, "rookie": false, "shootsCatches": "L", "rosterStatus": "Y", "currentTeam": {"id": 30, "name": "Minnesota Wild", "link": "/api/v1/teams/30"}, "primaryPosition": {"code": "G", "name": "Goalie", "type": "Goalie", "abbreviation": "G"}}]