[{"id": 8471769, "fullName": "Niklas Hjalmarsson", "link": "/api/v1/people/8471769", "firstName": "Niklas", "lastName": "Hjalmarsson", "primaryNumber": "4", "birthDate": "1987-06-06", "currentAge": 32, "birthCity": "Eksjo", "birthCountry": "SWE", "nationality": "SWE", "height": "6' 3\"", "weight": 197, "active": true, "alternateCaptain": true, "captain": false, "rookie": false, "shootsCatches": "L", "rosterStatus": "I", "currentTeam": {"id": 53, "name": "Arizona Coyotes", "link": "/api/v1/teams/53"}, "primaryPosition": {"code": "D", "name": "Defenseman", "type": "Defenseman", "abbreviation": "D"}}]