[{"id": 8473564, "fullName": "Michael Frolik", "link": "/api/v1/people/8473564", "firstName": "Michael", "lastName": "Frolik", "primaryNumber": "67", "birthDate": "1988-02-17", "currentAge": 31, "birthCity": "Kladno", "birthCountry": "CZE", "nationality": "CZE", "height": "6' 1\"", "weight": 190, "active": true, "alternateCaptain": false, "captain": false, "rookie": false, "shootsCatches": "L", "rosterStatus": "Y", "currentTeam": {"id": 20, "name": "Calgary Flames", "link": "/api/v1/teams/20"}, "primaryPosition": {"code": "R", "name": "Right Wing", "type": "Forward", "abbreviation": "RW"}}]