[{"id": 8474708, "fullName": "Alexander Pechurskiy", "link": "/api/v1/people/8474708", "firstName": "Alexander", "lastName": "Pechurskiy", "primaryNumber": "40", "birthDate": "1990-06-04", "currentAge": 29, "birthCity": "Magnitogorsk", "birthCountry": "RUS", "nationality": "RUS", "height": "6' 0\"", "weight": 187, "active": true, "alternateCaptain": false, "captain": false, "rookie": false, "shootsCatches": "L", "rosterStatus": "N", "currentTeam": {"id": 5, "name": "Pittsburgh Penguins", "link": "/api/v1/teams/5"}, "primaryPosition": {"code": "G", "name": "Goalie", "type": "Goalie", "abbreviation": "G"}}]