[{"id": 8474571, "fullName": "Mikkel Boedker", "link": "/api/v1/people/8474571", "firstName": "Mikkel", "lastName": "Boedker", "primaryNumber": "89", "birthDate": "1989-12-16", "currentAge": 29, "birthCity": "Brondby", "birthCountry": "DNK", "nationality": "DNK", "height": "5' 11\"", "weight": 207, "active": true, "alternateCaptain": false, "captain": false, "rookie": false, "shootsCatches": "L", "rosterStatus": "Y", "currentTeam": {"id": 9, "name": "Ottawa Senators", "link": "/api/v1/teams/9"}, "primaryPosition": {"code": "L", "name": "Left Wing", "type": "Forward", "abbreviation": "LW"}}]