[{"id": 8475726, "fullName": "Tyler Toffoli", "link": "/api/v1/people/8475726", "firstName": "Tyler", "lastName": "Toffoli", "primaryNumber": "73", "birthDate": "1992-04-24", "currentAge": 27, "birthCity": "Scarborough", "birthStateProvince": "ON", "birthCountry": "CAN", "nationality": "CAN", "height": "6' 0\"", "weight": 197, "active": true, "alternateCaptain": false, "captain": false, "rookie": false, "shootsCatches": "R", "rosterStatus": "Y", "currentTeam": {"id": 26, "name": "Los Angeles Kings", "link": "/api/v1/teams/26"}, "primaryPosition": {"code": "R", "name": "Right Wing", "type": "Forward", "abbreviation": "RW"}}]