[{"id": 8475283, "fullName": "Lane MacDermid", "link": "/api/v1/people/8475283", "firstName": "Lane", "lastName": "MacDermid", "primaryNumber": "28", "birthDate": "1989-08-25", "currentAge": 30, "birthCity": "Hartford", "birthStateProvince": "CT", "birthCountry": "USA", "nationality": "USA", "height": "6' 3\"", "weight": 215, "active": true, "alternateCaptain": false, "captain": false, "rookie": false, "shootsCatches": "L", "rosterStatus": "N", "currentTeam": {"id": 20, "name": "Calgary Flames", "link": "/api/v1/teams/20"}, "primaryPosition": {"code": "L", "name": "Left Wing", "type": "Forward", "abbreviation": "LW"}}]