[{"id": 8475200, "fullName": "Dmitry Orlov", "link": "/api/v1/people/8475200", "firstName": "Dmitry", "lastName": "Orlov", "primaryNumber": "9", "birthDate": "1991-07-23", "currentAge": 28, "birthCity": "Novokuznetsk", "birthCountry": "RUS", "nationality": "RUS", "height": "5' 11\"", "weight": 208, "active": true, "alternateCaptain": false, "captain": false, "rookie": false, "shootsCatches": "L", "rosterStatus": "Y", "currentTeam": {"id": 15, "name": "Washington Capitals", "link": "/api/v1/teams/15"}, "primaryPosition": {"code": "D", "name": "Defenseman", "type": "Defenseman", "abbreviation": "D"}}]