[{"id": 8476431, "fullName": "Adam Clendening", "link": "/api/v1/people/8476431", "firstName": "Adam", "lastName": "Clendening", "primaryNumber": "6", "birthDate": "1992-10-26", "currentAge": 27, "birthCity": "Niagara Falls", "birthStateProvince": "NY", "birthCountry": "USA", "nationality": "USA", "height": "6' 0\"", "weight": 189, "active": true, "alternateCaptain": false, "captain": false, "rookie": false, "shootsCatches": "R", "rosterStatus": "N", "currentTeam": {"id": 29, "name": "Columbus Blue Jackets", "link": "/api/v1/teams/29"}, "primaryPosition": {"code": "D", "name": "Defenseman", "type": "Defenseman", "abbreviation": "D"}}]