[{"id": 8476285, "fullName": "Matthew Peca", "link": "/api/v1/people/8476285", "firstName": "Matthew", "lastName": "Peca", "primaryNumber": "63", "birthDate": "1993-04-27", "currentAge": 26, "birthCity": "Petawawa", "birthStateProvince": "ON", "birthCountry": "CAN", "nationality": "CAN", "height": "5' 9\"", "weight": 182, "active": true, "alternateCaptain": false, "captain": false, "rookie": false, "shootsCatches": "L", "rosterStatus": "Y", "currentTeam": {"id": 8, "name": "Montr\u00e9al Canadiens", "link": "/api/v1/teams/8"}, "primaryPosition": {"code": "C", "name": "Center", "type": "Forward", "abbreviation": "C"}}]