[{"id": 8476432, "fullName": "Boone Jenner", "link": "/api/v1/people/8476432", "firstName": "Boone", "lastName": "Jenner", "primaryNumber": "38", "birthDate": "1993-06-15", "currentAge": 26, "birthCity": "Dorchester", "birthStateProvince": "ON", "birthCountry": "CAN", "nationality": "CAN", "height": "6' 2\"", "weight": 208, "active": true, "alternateCaptain": true, "captain": false, "rookie": false, "shootsCatches": "L", "rosterStatus": "Y", "currentTeam": {"id": 29, "name": "Columbus Blue Jackets", "link": "/api/v1/teams/29"}, "primaryPosition": {"code": "C", "name": "Center", "type": "Forward", "abbreviation": "C"}}]