[{"id": 8477021, "fullName": "Alexander Kerfoot", "link": "/api/v1/people/8477021", "firstName": "Alexander", "lastName": "Kerfoot", "primaryNumber": "15", "birthDate": "1994-08-11", "currentAge": 25, "birthCity": "Vancouver", "birthStateProvince": "BC", "birthCountry": "CAN", "nationality": "CAN", "height": "5' 10\"", "weight": 185, "active": true, "alternateCaptain": false, "captain": false, "rookie": false, "shootsCatches": "L", "rosterStatus": "Y", "currentTeam": {"id": 10, "name": "Toronto Maple Leafs", "link": "/api/v1/teams/10"}, "primaryPosition": {"code": "C", "name": "Center", "type": "Forward", "abbreviation": "C"}}]