[{"id": 8478397, "fullName": "Rasmus Andersson", "link": "/api/v1/people/8478397", "firstName": "Rasmus", "lastName": "Andersson", "primaryNumber": "4", "birthDate": "1996-10-27", "currentAge": 23, "birthCity": "Malm\u00f6", "birthCountry": "SWE", "nationality": "SWE", "height": "6' 1\"", "weight": 214, "active": true, "alternateCaptain": false, "captain": false, "rookie": false, "shootsCatches": "R", "rosterStatus": "Y", "currentTeam": {"id": 20, "name": "Calgary Flames", "link": "/api/v1/teams/20"}, "primaryPosition": {"code": "D", "name": "Defenseman", "type": "Defenseman", "abbreviation": "D"}}]