[{"id": 8478519, "fullName": "Anthony Cirelli", "link": "/api/v1/people/8478519", "firstName": "Anthony", "lastName": "Cirelli", "primaryNumber": "71", "birthDate": "1997-07-15", "currentAge": 22, "birthCity": "Etobicoke", "birthStateProvince": "ON", "birthCountry": "CAN", "nationality": "CAN", "height": "6' 0\"", "weight": 193, "active": true, "alternateCaptain": false, "captain": false, "rookie": false, "shootsCatches": "L", "rosterStatus": "Y", "currentTeam": {"id": 14, "name": "Tampa Bay Lightning", "link": "/api/v1/teams/14"}, "primaryPosition": {"code": "C", "name": "Center", "type": "Forward", "abbreviation": "C"}}]