[{"id": 8479388, "fullName": "Riley Stillman", "link": "/api/v1/people/8479388", "firstName": "Riley", "lastName": "Stillman", "primaryNumber": "61", "birthDate": "1998-03-09", "currentAge": 21, "birthCity": "Peterborough", "birthStateProvince": "ON", "birthCountry": "CAN", "nationality": "CAN", "height": "6' 1\"", "weight": 196, "active": true, "alternateCaptain": false, "captain": false, "rookie": true, "shootsCatches": "L", "rosterStatus": "N", "currentTeam": {"id": 13, "name": "Florida Panthers", "link": "/api/v1/teams/13"}, "primaryPosition": {"code": "D", "name": "Defenseman", "type": "Defenseman", "abbreviation": "D"}}]