[{"id": 8479644, "fullName": "Matt Luff", "link": "/api/v1/people/8479644", "firstName": "Matt", "lastName": "Luff", "primaryNumber": "64", "birthDate": "1997-05-05", "currentAge": 22, "birthCity": "Oakville", "birthStateProvince": "ON", "birthCountry": "CAN", "nationality": "CAN", "height": "6' 2\"", "weight": 196, "active": true, "alternateCaptain": false, "captain": false, "rookie": false, "shootsCatches": "R", "rosterStatus": "Y", "currentTeam": {"id": 26, "name": "Los Angeles Kings", "link": "/api/v1/teams/26"}, "primaryPosition": {"code": "R", "name": "Right Wing", "type": "Forward", "abbreviation": "RW"}}]