[{"id": 8480769, "fullName": "Joel L'Esperance", "link": "/api/v1/people/8480769", "firstName": "Joel", "lastName": "L'Esperance", "primaryNumber": "38", "birthDate": "1995-08-18", "currentAge": 24, "birthCity": "Brighton", "birthStateProvince": "MI", "birthCountry": "USA", "nationality": "USA", "height": "6' 2\"", "weight": 215, "active": true, "alternateCaptain": false, "captain": false, "rookie": true, "shootsCatches": "R", "rosterStatus": "N", "currentTeam": {"id": 25, "name": "Dallas Stars", "link": "/api/v1/teams/25"}, "primaryPosition": {"code": "C", "name": "Center", "type": "Forward", "abbreviation": "C"}}]